aiohttp_poe/__init__.py
aiohttp_poe/__main__.py
aiohttp_poe/base.py
aiohttp_poe/types.py
aiohttp_poe/samples/echo.py
aiohttp_poe-0.0.14.dist-info/METADATA
aiohttp_poe-0.0.14.dist-info/WHEEL
aiohttp_poe-0.0.14.dist-info/RECORD
