Metadata-Version: 2.1
Name: aiohttp_poe
Version: 0.0.14
Summary: A demonstration of the Poe protocol using aiohttp
Project-URL: Homepage, https://github.com/quora/poe-protocol
Author-email: Jelle Zijlstra <jelle@quora.com>
Classifier: License :: OSI Approved :: Apache Software License
Classifier: Operating System :: OS Independent
Classifier: Programming Language :: Python :: 3
Requires-Python: >=3.7
Requires-Dist: aiohttp
Requires-Dist: aiohttp-sse
Requires-Dist: typing-extensions
